{
  "$schema": "https://mintlify.com/docs.json",
  "theme": "mint",
  "name": "Stellar Passkey",
  "colors": {
    "primary": "#4F46E5",
    "light": "#818CF8",
    "dark": "#4338CA"
  },
  "appearance": {
    "default": "light"
  },
  "favicon": "/favicon.svg",
  "navigation": {
    "groups": [
      {
        "group": "Get started",
        "pages": [
          "introduction",
          "quickstart"
        ]
      },
      {
        "group": "SDK reference",
        "pages": [
          "sdk/overview",
          "sdk/create",
          "sdk/sign",
          "sdk/recover",
          "sdk/errors",
          "sdk/adapters"
        ]
      },
      {
        "group": "Components",
        "pages": [
          "components/overview",
          "components/create",
          "components/sign",
          "components/recover",
          "components/primitives"
        ]
      },
      {
        "group": "Stellar Wallets Kit",
        "pages": [
          "wallets-kit",
          "passkey-module"
        ]
      },
      {
        "group": "Reference",
        "pages": [
          "compatibility",
          "security"
        ]
      }
    ]
  },
  "navbar": {
    "primary": {
      "type": "button",
      "label": "GitHub",
      "href": "https://github.com/"
    }
  }
}
